decisionTable-0.0.3.dist-info/RECORD
decisionTable-0.0.3.dist-info/metadata.json
decisionTable-0.0.3.dist-info/top_level.txt
decisionTable-0.0.3.dist-info/WHEEL
decisionTable-0.0.3.dist-info/METADATA
decisionTable-0.0.3.dist-info/DESCRIPTION.rst
decisionTable/DecisionTable.py
decisionTable/__init__.py
decisionTable/view/Tli.py
decisionTable/view/__init__.py
