Metadata-Version: 2.0
Name: decisionTable
Version: 0.0.3
Summary: Transform decision table string to code logic.
Home-page: https://github.com/urosjarc/decisionTable
Author: Uroš Jarc
Author-email: jar.fmf@gmail.com
License: BSD
Keywords: decisionTable
Platform: UNKNOWN
Classifier: Development Status :: 2 - Pre-Alpha
Classifier: Intended Audience :: Developers
Classifier: License :: OSI Approved :: BSD License
Classifier: Natural Language :: English
Classifier: Programming Language :: Python :: 2
Classifier: Programming Language :: Python :: 2.6
Classifier: Programming Language :: Python :: 2.7
Classifier: Programming Language :: Python :: 3
Classifier: Programming Language :: Python :: 3.3
Classifier: Programming Language :: Python :: 3.4
